quickalias.py
quickalias-3.1.4.dist-info/LICENSE
quickalias-3.1.4.dist-info/METADATA
quickalias-3.1.4.dist-info/WHEEL
quickalias-3.1.4.dist-info/entry_points.txt
quickalias-3.1.4.dist-info/top_level.txt
quickalias-3.1.4.dist-info/RECORD
