Metadata-Version: 2.1
Name: quickalias
Version: 3.1.4
Summary: Creates permanent aliases
Home-page: https://github.com/dCaples/quickalias
Author: Decator (Aidan Neal) & dCaples
Author-email: decator.c@proton.me
License: GPLv3
Keywords: python,alias,shell,config,scriptable,commandline
Platform: UNKNOWN
Classifier: Development Status :: 4 - Beta
Classifier: Programming Language :: Python :: 3
Classifier: Intended Audience :: End Users/Desktop
Classifier: Operating System :: Unix
Classifier: Operating System :: MacOS :: MacOS X
License-File: LICENSE
